countries_dictionary/__init__.py
countries_dictionary/iso_finder.py
countries_dictionary/quick_functions.py
countries_dictionary/russia.py
countries_dictionary/united_states.py
countries_dictionary/vietnam.py
countries_dictionary/unrecognised_states/__init__.py
countries_dictionary/unrecognised_states/transnistria.py
countries_dictionary-5.1.3.dist-info/licenses/LICENCE
countries_dictionary-5.1.3.dist-info/METADATA
countries_dictionary-5.1.3.dist-info/WHEEL
countries_dictionary-5.1.3.dist-info/top_level.txt
countries_dictionary-5.1.3.dist-info/RECORD
