Metadata-Version: 2.4
Name: countries_dictionary
Version: 5.1.3
Summary: Provides a dictionary contains countries and unrecognised states and information about them
Author-email: Ngô Trần Quang Thiện <quangthienngotran@gmail.com>
License:                     GNU GENERAL PUBLIC LICENSE
Project-URL: Homepage, https://github.com/ThienFakeVN/countries_dictionary/
Project-URL: Repository, https://github.com/ThienFakeVN/countries_dictionary/
Keywords: countries,states,dictionary,united nations,iso
Requires-Python: >=3.7
License-File: LICENCE
Dynamic: license-file
